spiders_for_all/__init__.py
spiders_for_all/__main__.py
spiders_for_all/conf/__init__.py
spiders_for_all/conf/settings.py
spiders_for_all/const.py
spiders_for_all/core/__init__.py
spiders_for_all/core/client.py
spiders_for_all/core/downloader.py
spiders_for_all/core/exception.py
spiders_for_all/core/media.py
spiders_for_all/core/response.py
spiders_for_all/core/spider.py
spiders_for_all/database/__init__.py
spiders_for_all/database/__main__.py
spiders_for_all/database/cli.py
spiders_for_all/database/manager.py
spiders_for_all/database/schema.py
spiders_for_all/database/session.py
spiders_for_all/spiders/__init__.py
spiders_for_all/spiders/bilibili/README.md
spiders_for_all/spiders/bilibili/__init__.py
spiders_for_all/spiders/bilibili/__main__.py
spiders_for_all/spiders/bilibili/analysis.py
spiders_for_all/spiders/bilibili/cli.py
spiders_for_all/spiders/bilibili/const.py
spiders_for_all/spiders/bilibili/db.py
spiders_for_all/spiders/bilibili/downloader.py
spiders_for_all/spiders/bilibili/models.py
spiders_for_all/spiders/bilibili/patterns.py
spiders_for_all/spiders/bilibili/schema.py
spiders_for_all/spiders/bilibili/sign.py
spiders_for_all/spiders/bilibili/spiders.py
spiders_for_all/spiders/bilibili/utils.py
spiders_for_all/spiders/xhs/README.md
spiders_for_all/spiders/xhs/__init__.py
spiders_for_all/spiders/xhs/__main__.py
spiders_for_all/spiders/xhs/analysis.py
spiders_for_all/spiders/xhs/cli.py
spiders_for_all/spiders/xhs/const.py
spiders_for_all/spiders/xhs/db.py
spiders_for_all/spiders/xhs/downloader.py
spiders_for_all/spiders/xhs/models.py
spiders_for_all/spiders/xhs/patterns.py
spiders_for_all/spiders/xhs/schema.py
spiders_for_all/spiders/xhs/sign.py
spiders_for_all/spiders/xhs/spiders.py
spiders_for_all/static/xhs.js
spiders_for_all/utils/__init__.py
spiders_for_all/utils/decorator.py
spiders_for_all/utils/helper.py
spiders_for_all/utils/logger.py
spiders_for_all-0.3.9.dist-info/METADATA
spiders_for_all-0.3.9.dist-info/WHEEL
spiders_for_all-0.3.9.dist-info/RECORD
