Metadata-Version: 2.1
Name: spiders-for-all
Version: 0.3.9
Summary: 
Author: icebear
Author-email: iiiicebeaaaar@gmail.com
Requires-Python: >=3.12,<4.0
Classifier: Programming Language :: Python :: 3
Classifier: Programming Language :: Python :: 3.12
Requires-Dist: beautifulsoup4 (>=4.12.2,<5.0.0)
Requires-Dist: click (>=8.1.7,<9.0.0)
Requires-Dist: environs (>=9.5.0,<10.0.0)
Requires-Dist: fake-useragent (>=1.4.0,<2.0.0)
Requires-Dist: pydantic (>=2.5.2,<3.0.0)
Requires-Dist: pyexecjs (>=1.5.1,<2.0.0)
Requires-Dist: requests (>=2.31.0,<3.0.0)
Requires-Dist: rich (>=13.7.0,<14.0.0)
Requires-Dist: sqlalchemy (>=2.0.23,<3.0.0)
Requires-Dist: types-beautifulsoup4 (>=4.12.0.7,<5.0.0.0)
